{
  "title": "Fire Punch",
  "description": "In the not-too-distant past, the Ice Witch blanketed the world in snow, starvation and madness, leading the inhabitants to seek their salvation in fire. With that, an unusual destiny unfolds for two young orphans, Agni and Luna, blessed with the ability to regenerate. But will this ability prove to be more of a curse than a blessing?",
  "artist": "Tatsuki Fujimoto",
  "author": "Tatsuki Fujimoto",
  "cover": "https://mangadex.org/covers/6fef1f74-a0ad-4f0d-99db-d32a7cd24098/b437f317-6f1e-48ae-a8a0-54cdd2abfd2f.jpg",
  "chapters": {
    "1": {
      "title": "",
      "volume": "1",
      "last_updated": "1516088938",
      "groups": {
        "VIZ Media": "/proxy/api/imgur/chapter/oc7UWY9"
      }
    },
    "2": {
      "title": "",
      "volume": "1",
      "last_updated": "1516089212",
      "groups": {
        "VIZ Media": "/proxy/api/imgur/chapter/9NHHqQa"
      }
    },
    "3": {
      "title": "",
      "volume": "1",
      "last_updated": "1516089256",
      "groups": {
        "VIZ Media": "/proxy/api/imgur/chapter/qbTHOr9"
      }
    },
    "4": {
      "title": "",
      "volume": "1",
      "last_updated": "1516089356",
      "groups": {
        "VIZ Media": "/proxy/api/imgur/chapter/rVqTsEH"
      }
    },
    "5": {
      "title": "",
      "volume": "1",
      "last_updated": "1516089375",
      "groups": {
        "VIZ Media": "/proxy/api/imgur/chapter/scXN8dT"
      }
    },
    "6": {
      "title": "",
      "volume": "1",
      "last_updated": "1516089389",
      "groups": {
        "VIZ Media": "/proxy/api/imgur/chapter/WPWHodq"
      }
    },
    "7": {
      "title": "",
      "volume": "1",
      "last_updated": "1516089405",
      "groups": {
        "VIZ Media": "/proxy/api/imgur/chapter/Kkrs9dB"
      }
    },
    "8": {
      "title": "",
      "volume": "1",
      "last_updated": "1516089458",
      "groups": {
        "VIZ Media": "/proxy/api/imgur/chapter/VTacAet"
      }
    },
    "9": {
      "title": "",
      "volume": "2",
      "last_updated": "1523951870",
      "groups": {
        "VIZ Media": "/proxy/api/imgur/chapter/XLur5ra"
      }
    },
    "10": {
      "title": "",
      "volume": "2",
      "last_updated": "1523951891",
      "groups": {
        "VIZ Media": "/proxy/api/imgur/chapter/UqvdgDj"
      }
    },
    "11": {
      "title": "",
      "volume": "2",
      "last_updated": "1523951911",
      "groups": {
        "VIZ Media": "/proxy/api/imgur/chapter/ezgwZGK"
      }
    },
    "12": {
      "title": "",
      "volume": "2",
      "last_updated": "1523951925",
      "groups": {
        "VIZ Media": "/proxy/api/imgur/chapter/mNxERph"
      }
    },
    "13": {
      "title": "",
      "volume": "2",
      "last_updated": "1523952024",
      "groups": {
        "VIZ Media": "/proxy/api/imgur/chapter/yxpwkpe"
      }
    },
    "14": {
      "title": "",
      "volume": "2",
      "last_updated": "1523952039",
      "groups": {
        "VIZ Media": "/proxy/api/imgur/chapter/QhYahrr"
      }
    },
    "15": {
      "title": "",
      "volume": "2",
      "last_updated": "1523952057",
      "groups": {
        "VIZ Media": "/proxy/api/imgur/chapter/IohEYMG"
      }
    },
    "16": {
      "title": "",
      "volume": "2",
      "last_updated": "1523952090",
      "groups": {
        "VIZ Media": "/proxy/api/imgur/chapter/GIZYl3s"
      }
    },
    "17": {
      "title": "",
      "volume": "2",
      "last_updated": "1523952111",
      "groups": {
        "VIZ Media": "/proxy/api/imgur/chapter/XgGAuzs"
      }
    },
    "18": {
      "title": "",
      "volume": "2",
      "last_updated": "1523952123",
      "groups": {
        "VIZ Media": "/proxy/api/imgur/chapter/QeKrmay"
      }
    },
    "19": {
      "title": "",
      "volume": "3",
      "last_updated": "1531814533",
      "groups": {
        "VIZ Media": "/proxy/api/imgur/chapter/hkoSmRF"
      }
    },
    "20": {
      "title": "",
      "volume": "3",
      "last_updated": "1531814618",
      "groups": {
        "VIZ Media": "/proxy/api/imgur/chapter/18ume7s"
      }
    },
    "21": {
      "title": "",
      "volume": "3",
      "last_updated": "1531814681",
      "groups": {
        "VIZ Media": "/proxy/api/imgur/chapter/1O1lZMl"
      }
    },
    "22": {
      "title": "",
      "volume": "3",
      "last_updated": "1531814696",
      "groups": {
        "VIZ Media": "/proxy/api/imgur/chapter/CAvFeF1"
      }
    },
    "23": {
      "title": "",
      "volume": "3",
      "last_updated": "1531814715",
      "groups": {
        "VIZ Media": "/proxy/api/imgur/chapter/hc5VTBl"
      }
    },
    "24": {
      "title": "",
      "volume": "3",
      "last_updated": "1531814726",
      "groups": {
        "VIZ Media": "/proxy/api/imgur/chapter/Ay9dh33"
      }
    },
    "25": {
      "title": "",
      "volume": "3",
      "last_updated": "1531814737",
      "groups": {
        "VIZ Media": "/proxy/api/imgur/chapter/OskhqZ4"
      }
    },
    "26": {
      "title": "",
      "volume": "3",
      "last_updated": "1531814748",
      "groups": {
        "VIZ Media": "/proxy/api/imgur/chapter/iQXvyuO"
      }
    },
    "27": {
      "title": "",
      "volume": "3",
      "last_updated": "1531814763",
      "groups": {
        "VIZ Media": "/proxy/api/imgur/chapter/MTf9AR3"
      }
    },
    "28": {
      "title": "",
      "volume": "3",
      "last_updated": "1531814788",
      "groups": {
        "VIZ Media": "/proxy/api/imgur/chapter/HN4Kzko"
      }
    },
    "29": {
      "title": "",
      "volume": "4",
      "last_updated": "1539677425",
      "groups": {
        "VIZ Media": "/proxy/api/imgur/chapter/g2RJu8o"
      }
    },
    "30": {
      "title": "",
      "volume": "4",
      "last_updated": "1539677481",
      "groups": {
        "VIZ Media": "/proxy/api/imgur/chapter/kDk8kNs"
      }
    },
    "31": {
      "title": "",
      "volume": "4",
      "last_updated": "1539677579",
      "groups": {
        "VIZ Media": "/proxy/api/imgur/chapter/NQYKamd"
      }
    },
    "32": {
      "title": "",
      "volume": "4",
      "last_updated": "1539677590",
      "groups": {
        "VIZ Media": "/proxy/api/imgur/chapter/ek8eEKA"
      }
    },
    "33": {
      "title": "",
      "volume": "4",
      "last_updated": "1539677605",
      "groups": {
        "VIZ Media": "/proxy/api/imgur/chapter/1DMfaCk"
      }
    },
    "34": {
      "title": "",
      "volume": "4",
      "last_updated": "1539677617",
      "groups": {
        "VIZ Media": "/proxy/api/imgur/chapter/NtuIy4T"
      }
    },
    "35": {
      "title": "",
      "volume": "4",
      "last_updated": "1539677630",
      "groups": {
        "VIZ Media": "/proxy/api/imgur/chapter/sFR1XHd"
      }
    },
    "36": {
      "title": "",
      "volume": "4",
      "last_updated": "1539677643",
      "groups": {
        "VIZ Media": "/proxy/api/imgur/chapter/qy23jFs"
      }
    },
    "37": {
      "title": "",
      "volume": "4",
      "last_updated": "1539677656",
      "groups": {
        "VIZ Media": "/proxy/api/imgur/chapter/Yg4KRd0"
      }
    },
    "38": {
      "title": "",
      "volume": "4",
      "last_updated": "1539677668",
      "groups": {
        "VIZ Media": "/proxy/api/imgur/chapter/OAhqIWJ"
      }
    },
    "39": {
      "title": "",
      "volume": "4",
      "last_updated": "1539677684",
      "groups": {
        "VIZ Media": "/proxy/api/imgur/chapter/y0mqIaq"
      }
    }
  }
}